retropath2_wrapper/RetroPath2.py
retropath2_wrapper/__init__.py
retropath2_wrapper/__main__.py
retropath2_wrapper/workflow/RetroPath2.0-v9.knwf
retropath2_wrapper-1.1.0.dist-info/LICENSE.txt
retropath2_wrapper-1.1.0.dist-info/METADATA
retropath2_wrapper-1.1.0.dist-info/WHEEL
retropath2_wrapper-1.1.0.dist-info/top_level.txt
retropath2_wrapper-1.1.0.dist-info/RECORD
