Metadata-Version: 2.1
Name: retropath2-wrapper
Version: 1.1.0
Summary: 'python wrapper to run retropath2.0 knime workflow'
Home-page: https://github.com/brsynth/retropath2-wrapper
Author: 'melchior du lac, joan hérisson'
Author-email: joan.herisson@univ-evry.fr
License: MIT
Platform: UNKNOWN
Classifier: Programming Language :: Python :: 3
Classifier: License :: OSI Approved :: MIT License
Classifier: Operating System :: OS Independent
Requires-Python: >=3.5
Requires-Dist: brs-utils
